{
  "photo": {
    "id": "14940690236",
    "secret": "2befb7e1bd",
    "server": "3900",
    "farm": 4,
    "dateuploaded": "1408402699",
    "isfavorite": 0,
    "license": "0",
    "safety_level": "0",
    "rotation": 0,
    "owner": {
      "nsid": "97402095@N00",
      "username": "Trish Mayo",
      "realname": "",
      "location": "New York, US",
      "iconserver": "107",
      "iconfarm": 1,
      "path_alias": "obsessivephotography"
    },
    "title": {
      "_content": "Sunny Afternoon With St Christopher"
    },
    "description": {
      "_content": "A beautiful light and shadow pattern at the Met Museum.\n\nInformation about the large Fresco on the left\nSaint Christopher and the Infant Christ\nDomenico Ghirlandaio (Domenico Bigordi) \n(Italian, Florence 1448/49–1494 Florence)\nMedium: Fresco\nDimensions: 112 x 59 in. (284.5 x 149.9 cm)\nClassification: Paintings\nCredit Line: Gift of Cornelius Vanderbilt, 1880\nAccession Number: 80.3.674"
    },
    "visibility": {
      "ispublic": 1,
      "isfriend": 0,
      "isfamily": 0
    },
    "dates": {
      "posted": "1408402699",
      "taken": "2014-08-18 13:56:06",
      "takengranularity": "0",
      "takenunknown": 0,
      "lastupdate": "1411520038"
    },
    "views": "745",
    "editability": {
      "cancomment": 0,
      "canaddmeta": 0
    },
    "publiceditability": {
      "cancomment": 1,
      "canaddmeta": 0
    },
    "usage": {
      "candownload": 0,
      "canblog": 0,
      "canprint": 0,
      "canshare": 1
    },
    "comments": {
      "_content": "33"
    },
    "notes": {
      "note": []
    },
    "people": {
      "haspeople": 0
    },
    "tags": {
      "tag": [
        {
          "id": "4958480-14940690236-607",
          "author": "97402095@N00",
          "authorname": "Trish Mayo",
          "raw": "art",
          "_content": "art",
          "machine_tag": 0
        },
        {
          "id": "4958480-14940690236-1500",
          "author": "97402095@N00",
          "authorname": "Trish Mayo",
          "raw": "painting",
          "_content": "painting",
          "machine_tag": 0
        },
        {
          "id": "4958480-14940690236-48334",
          "author": "97402095@N00",
          "authorname": "Trish Mayo",
          "raw": "fresco",
          "_content": "fresco",
          "machine_tag": 0
        },
        {
          "id": "4958480-14940690236-1154",
          "author": "97402095@N00",
          "authorname": "Trish Mayo",
          "raw": "museum",
          "_content": "museum",
          "machine_tag": 0
        },
        {
          "id": "4958480-14940690236-3789",
          "author": "97402095@N00",
          "authorname": "Trish Mayo",
          "raw": "shadows",
          "_content": "shadows",
          "machine_tag": 0
        },
        {
          "id": "4958480-14940690236-216",
          "author": "97402095@N00",
          "authorname": "Trish Mayo",
          "raw": "light",
          "_content": "light",
          "machine_tag": 0
        },
        {
          "id": "4958480-14940690236-202756",
          "author": "97402095@N00",
          "authorname": "Trish Mayo",
          "raw": "Met Museum",
          "_content": "metmuseum",
          "machine_tag": 0
        },
        {
          "id": "4958480-14940690236-59219",
          "author": "97402095@N00",
          "authorname": "Trish Mayo",
          "raw": "Metropolitan Museum",
          "_content": "metropolitanmuseum",
          "machine_tag": 0
        },
        {
          "id": "4958480-14940690236-97327",
          "author": "97402095@N00",
          "authorname": "Trish Mayo",
          "raw": "Metropolitan Museum of Art",
          "_content": "metropolitanmuseumofart",
          "machine_tag": 0
        },
        {
          "id": "4958480-14940690236-17345460",
          "author": "97402095@N00",
          "authorname": "Trish Mayo",
          "raw": "GününEnİyisi",
          "_content": "gününeniyisi",
          "machine_tag": 0
        },
        {
          "id": "4958480-14940690236-17278851",
          "author": "97402095@N00",
          "authorname": "Trish Mayo",
          "raw": "TheBestOfDay",
          "_content": "thebestofday",
          "machine_tag": 0
        }
      ]
    },
    "urls": {
      "url": [
        {
          "type": "photopage",
          "_content": "https://www.flickr.com/photos/obsessivephotography/14940690236/"
        }
      ]
    },
    "media": "photo"
  },
  "stat": "ok"
}