{
  "photo": {
    "id": "7105479261",
    "secret": "8ae1988dee",
    "server": "7218",
    "farm": 8,
    "dateuploaded": "1335171918",
    "isfavorite": 0,
    "license": "0",
    "safety_level": "0",
    "rotation": 0,
    "owner": {
      "nsid": "26270547@N07",
      "username": "rverc",
      "realname": "Regan Vercruysse",
      "location": "Stewartsville, New Jersey, USA",
      "iconserver": "2319",
      "iconfarm": 3,
      "path_alias": "rverc"
    },
    "title": {
      "_content": "TheMountainFord_TheMET(6)"
    },
    "description": {
      "_content": "Thomas Cole (1801-1848)\n\n<b><i> The Mountain Ford </i></b>   1846\nOil on canvas\n\nPainted two years before Cole’s early death, this picture appears to be the record of an entirely imagined vision, with an implied symbolic meaning.  The mountain in the center, with light at its summit and shadow at its base, dwarfs and dominates the forest around it.  Civilization has laid no mark on pure nature.  Just at the edge of a murky body of water, however, a horseman appears on a hesitating white mount, pausing momentarily before plunging in to ford the dark and frightening depths.  This confrontation of man and wilderness draws on the long allegorical tradition of a lonely rider journeying through an awesome world\n\nBequest of Maria DeWitt Jesup, from the collection of her husband, Morris K. Jesup, 1914\n15.30.63\n\nFrom the placard:  Metropolitan Museum of Art\n"
    },
    "visibility": {
      "ispublic": 1,
      "isfriend": 0,
      "isfamily": 0
    },
    "dates": {
      "posted": "1335171918",
      "taken": "2011-02-25 12:20:19",
      "takengranularity": "0",
      "takenunknown": 0,
      "lastupdate": "1335234026"
    },
    "views": "189",
    "editability": {
      "cancomment": 0,
      "canaddmeta": 0
    },
    "publiceditability": {
      "cancomment": 1,
      "canaddmeta": 0
    },
    "usage": {
      "candownload": 0,
      "canblog": 0,
      "canprint": 0,
      "canshare": 1
    },
    "comments": {
      "_content": "1"
    },
    "notes": {
      "note": []
    },
    "people": {
      "haspeople": 0
    },
    "tags": {
      "tag": [
        {
          "id": "26249217-7105479261-59219",
          "author": "26270547@N07",
          "authorname": "rverc",
          "raw": "Metropolitan_Museum",
          "_content": "metropolitanmuseum",
          "machine_tag": 0
        },
        {
          "id": "26249217-7105479261-607",
          "author": "26270547@N07",
          "authorname": "rverc",
          "raw": "Art",
          "_content": "art",
          "machine_tag": 0
        },
        {
          "id": "26249217-7105479261-106",
          "author": "26270547@N07",
          "authorname": "rverc",
          "raw": "NYC",
          "_content": "nyc",
          "machine_tag": 0
        },
        {
          "id": "26249217-7105479261-29750",
          "author": "26270547@N07",
          "authorname": "rverc",
          "raw": "MET",
          "_content": "met",
          "machine_tag": 0
        }
      ]
    },
    "urls": {
      "url": [
        {
          "type": "photopage",
          "_content": "https://www.flickr.com/photos/rverc/7105479261/"
        }
      ]
    },
    "media": "photo"
  },
  "stat": "ok"
}